odoo/addons/product_state/README.rst
odoo/addons/product_state/__init__.py
odoo/addons/product_state/__manifest__.py
odoo/addons/product_state/hooks.py
odoo/addons/product_state/data/product_state_data.xml
odoo/addons/product_state/i18n/ca.po
odoo/addons/product_state/i18n/de.po
odoo/addons/product_state/i18n/es.po
odoo/addons/product_state/i18n/fr.po
odoo/addons/product_state/i18n/hr.po
odoo/addons/product_state/i18n/nl_NL.po
odoo/addons/product_state/i18n/product_state.pot
odoo/addons/product_state/i18n/pt.po
odoo/addons/product_state/i18n/sl.po
odoo/addons/product_state/migrations/12.0.2.0.0/post-migration.py
odoo/addons/product_state/models/__init__.py
odoo/addons/product_state/models/product_template.py
odoo/addons/product_state/readme/CONTRIBUTORS.rst
odoo/addons/product_state/readme/DESCRIPTION.rst
odoo/addons/product_state/readme/USAGE.rst
odoo/addons/product_state/security/ir.model.access.csv
odoo/addons/product_state/static/description/icon.png
odoo/addons/product_state/static/description/index.html
odoo/addons/product_state/views/product_views.xml
odoo12_addon_product_state-12.0.2.0.2.dist-info/METADATA
odoo12_addon_product_state-12.0.2.0.2.dist-info/WHEEL
odoo12_addon_product_state-12.0.2.0.2.dist-info/top_level.txt
odoo12_addon_product_state-12.0.2.0.2.dist-info/RECORD
