Metadata-Version: 2.1
Name: odoo12-addon-product-state
Version: 12.0.2.0.2
Summary: Module introducing a state field on product template
Home-page: https://github.com/OCA/product-attribute
Author: ACSONE SA/NV, Odoo Community Association (OCA)
Author-email: support@odoo-community.org
License: AGPL-3
Platform: UNKNOWN
Classifier: Programming Language :: Python
Classifier: Framework :: Odoo
Classifier: License :: OSI Approved :: GNU Affero General Public License v3
Requires-Python: >=3.5
Requires-Dist: odoo (<12.1dev,>=12.0a)
